{
    "$schema": "https://schema.management.azure.com/schemas/2015-01-01/deploymentTemplate.json#",
    "contentVersion": "1.0.0.0",
    "parameters": {
        "kubernetesSettings": {
            "type": "object"
        }
    },
    "resources": [
        {
            "type": "Microsoft.ContainerService/managedClusters",
            "name": "[parameters('kubernetesSettings').servicename]",
            "apiVersion": "2018-03-31",
           "location": "[parameters('kubernetesSettings').location]",
            "tags": {},
            "properties": {
                "kubernetesVersion": "[parameters('kubernetesSettings').kubernetesVersion]",
               "enableRBAC": "[parameters('kubernetesSettings').enableRBAC]",
                "dnsPrefix": "[parameters('kubernetesSettings').dnsPrefix]",
                "addonProfiles": {
                    "httpApplicationRouting": {
                       "enabled":  "[parameters('kubernetesSettings').enableHttpApplicationRouting]"
                    }
                },
                "agentPoolProfiles": [
                    {
                        "name": "agentpool",
                        "osDiskSizeGB": "[parameters('kubernetesSettings').osDiskSizeGB]",
                       "count": "[parameters('kubernetesSettings').agentCount]",
                        "vmSize": "[parameters('kubernetesSettings').agentVMSize]",
                        "osType": "[parameters('kubernetesSettings').osType]",
                        "storageProfile": "ManagedDisks"
                    }
                ],
                "servicePrincipalProfile": {
                    "ClientId": "[parameters('kubernetesSettings').servicePrincipalClientId]",
                    "Secret":"[parameters('kubernetesSettings').servicePrincipalClientSecret]"
                },
                "networkProfile": {
                    "networkPlugin": "[parameters('kubernetesSettings').networkPlugin]",
                    "podCidr": "10.244.0.0/16",
                    "serviceCidr": "10.0.0.0/16",
                    "dnsServiceIP": "10.0.0.10",
                    "dockerBridgeCidr": "172.17.0.1/16"
                }
            }

        }
    ],
    "outputs": {
        "controlPlaneFQDN": {
            "type": "string",
            "value": "[reference(concat('Microsoft.ContainerService/managedClusters/', parameters('kubernetesSettings').servicename)).fqdn]"
        }
    }
}
